CHANGES.md
LICENSE
MANIFEST.in
README.md
django_explain.py
setup.py
django_explain.egg-info/PKG-INFO
django_explain.egg-info/SOURCES.txt
django_explain.egg-info/dependency_links.txt
django_explain.egg-info/requires.txt
django_explain.egg-info/top_level.txt