Metadata-Version: 1.1
Name: django-explain
Version: 1.1
Summary: A helper to get EXPLAIN and EXPLAIN ANALYZE OUTPUT for django queryset.
Home-page: UNKNOWN
Author: Egor Orlov
Author-email: oeegor@gmail.com
License: MIT License
Platform: any
Classifier: Environment :: Web Environment
Classifier: Intended Audience :: Developers
Classifier: License :: OSI Approved :: MIT License
Classifier: Operating System :: OS Independent
Classifier: Programming Language :: Python
Classifier: Programming Language :: Python :: 2.7
Classifier: Programming Language :: Python :: 3.5
Classifier: Topic :: Internet :: WWW/HTTP
Classifier: Topic :: Internet :: WWW/HTTP :: Dynamic Content
